{
    "id": "nl-core-practitionerrole-02",
    "referenceId": "PractitionerRole/nl-core-practitionerrole-02",
    "resourceType": "PractitionerRole",
    "profile": "http://fhir.nl/fhir/StructureDefinition/nl-core-practitionerrole",
    "fhirVersion": "R3",
    "identifier": [
        {
            "_type": "identifier",
            "use": null,
            "system": "urn:oid:2.16.840.1.113883.2.4.3.11.999.7.6",
            "value": "170fed17-8fdf-11ec-1686-020000000000",
            "type": null
        }
    ],
    "telecom": null,
    "organization": {
        "_type": "reference",
        "reference": "Organization/nl-core-organization-01",
        "display": "Maatschap Vaste Huisarts"
    },
    "specialty": {
        "_type": "codeableConcept",
        "text": null,
        "coding": [
            {
                "code": "0100",
                "display": "Huisartsen, niet nader gespecificeerd",
                "system": "urn:oid:2.16.840.1.113883.2.4.6.7"
            }
        ]
    }
}