{
    "label": "Toedieningsschema",
    "children": [
        {
            "label": "Begin datum",
            "type": "SINGLE_VALUE",
            "value": {
                "display": "6 februari 2019"
            }
        },
        {
            "label": "Eind datum",
            "type": "SINGLE_VALUE",
            "value": {
                "display": "9 februari 2019"
            }
        },
        {
            "label": "Toedieninsgduur",
            "value": {
                "display": "30 d"
            },
            "type": "SINGLE_VALUE"
        },
        {
            "label": "Frequentie",
            "type": "SINGLE_VALUE",
            "value": {
                "display": "2"
            }
        },
        {
            "label": "Maximum waarde",
            "type": "SINGLE_VALUE",
            "value": {
                "display": "20"
            }
        },
        {
            "label": "Interval",
            "value": {
                "display": "1 d"
            },
            "type": "SINGLE_VALUE"
        },
        {
            "label": "Weekdagen",
            "type": "MULTIPLE_VALUES",
            "value": [
                {
                    "display": "mon"
                },
                {
                    "display": "tue"
                }
            ]
        },
        {
            "label": "Toedientijd",
            "type": "MULTIPLE_VALUES",
            "value": [
                {
                    "display": "08:00:00"
                },
                {
                    "display": "18:00:00"
                }
            ]
        },
        {
            "label": "Dagdeel",
            "type": "MULTIPLE_VALUES",
            "value": [
                {
                    "display": "73775008"
                }
            ]
        }
    ]
}