{
    "label": "Contact",
    "children": [
        {
            "children": [
                {
                    "label": "Begin datum",
                    "type": "SINGLE_VALUE",
                    "display": "8 februari 2013"
                },
                {
                    "label": "Eind datum",
                    "type": "SINGLE_VALUE",
                    "display": "8 februari 2013"
                },
                {
                    "label": "Identificatie",
                    "type": "MULTIPLE_VALUES",
                    "display": [
                        "123456",
                        "1506f28b-8fdf-11ec-1151-020000000000"
                    ]
                },
                {
                    "label": "Onderwerp",
                    "type": "REFERENCE_VALUE",
                    "display": "J. XXX_Helleman (Johan)",
                    "reference": "Patient/nl-core-patient-01"
                },
                {
                    "label": "r3.gp_encounter.class",
                    "type": "SINGLE_VALUE",
                    "display": "inpatient encounter (IMP in code systeem http://hl7.org/fhir/v3/ActCode)"
                },
                {
                    "label": "r3.gp_encounter.diagnosis",
                    "type": "SINGLE_VALUE",
                    "display": null
                },
                {
                    "label": "r3.gp_encounter.reason",
                    "type": "SINGLE_VALUE",
                    "display": null
                },
                {
                    "label": "r3.gp_encounter.service_provider",
                    "type": "REFERENCE_VALUE",
                    "display": "Huisartspraktijk (zelfstandig of groepspraktijk)",
                    "reference": "Organization/nl-core-organization-01"
                }
            ]
        },
        {
            "label": "r3.gp_encounter.participant",
            "children": [
                {
                    "label": "r3.gp_encounter.participant.individual",
                    "type": "REFERENCE_VALUE",
                    "display": "Henk de Vries",
                    "reference": "Practitioner/nl-core-practitioner-01"
                },
                {
                    "label": "r3.gp_encounter.participant.type.health_professional_role",
                    "type": "SINGLE_VALUE",
                    "display": null
                }
            ]
        },
        {
            "label": "r3.gp_encounter.hospitalization",
            "children": [
                {
                    "label": "r3.gp_encounter.hospitalization.admit_source",
                    "type": "SINGLE_VALUE",
                    "display": null
                },
                {
                    "label": "r3.gp_encounter.hospitalization.discharge_disposition",
                    "type": "SINGLE_VALUE",
                    "display": null
                }
            ]
        }
    ]
}